{"id":180866605,"repository_id":4817619,"number":"3957","state":"finished","result":null,"started_at":"2016-12-02T23:57:01Z","finished_at":"2016-12-03T00:46:08Z","duration":2947,"commit":"514dbd5bbc0433143fd746bbc641bfb05ee2c544","branch":"simple_service","message":"Merge in master\n\nHad to regenerate the pps proto file","event_type":"push"}
{"id":180865646,"repository_id":4817619,"number":"3955","state":"finished","result":null,"started_at":"2016-12-02T23:51:56Z","finished_at":"2016-12-02T23:56:07Z","duration":251,"commit":"1cdc98bb01d54194c5d0691dcdadf87084fb865e","branch":"simple_service","message":"Rebuild proto files / propagate comment to pb file","event_type":"push"}
{"id":180862722,"repository_id":4817619,"number":"3953","state":"finished","result":0,"started_at":"2016-12-02T23:39:48Z","finished_at":"2016-12-03T00:00:32Z","duration":1244,"commit":"367ea4ca4624bf20a385d7cac746bcb712f9da6f","branch":"custom_release_docs","message":"Fix typos","event_type":"push"}
{"id":180848399,"repository_id":4817619,"number":"3951","state":"finished","result":0,"started_at":"2016-12-02T22:38:35Z","finished_at":"2016-12-02T23:14:15Z","duration":2140,"commit":"3e86f0ccd901bf116be4583a468a23bc090282f1","branch":"downgrade-rethink","message":"Downgrade rethinkdb to 2.3.2\n\nBecause starting from 2.3.3 rethinkdb seems to have a memory leak issue.","event_type":"push"}
{"id":180843370,"repository_id":4817619,"number":"3949","state":"finished","result":0,"started_at":"2016-12-02T22:16:38Z","finished_at":"2016-12-02T22:37:53Z","duration":1275,"commit":"0757e3b13ff77592456ce1c56b08754c92d03ff7","branch":"custom_release_docs","message":"Omit paste","event_type":"push"}
{"id":180841295,"repository_id":4817619,"number":"3947","state":"finished","result":1,"started_at":"2016-12-02T22:08:55Z","finished_at":"2016-12-02T22:56:17Z","duration":2842,"commit":"828e4d32d1f3b1bb8285765463be5003af75be72","branch":"custom_release_docs","message":"Add custom release instructions","event_type":"push"}
{"id":180834116,"repository_id":4817619,"number":"3945","state":"finished","result":0,"started_at":"2016-12-02T21:41:21Z","finished_at":"2016-12-02T22:01:47Z","duration":1226,"commit":"78764f7ed902d2e90d11f48edadeb407236372d5","branch":"pipe_input","message":"Whoops, we should close those pipes too.","event_type":"push"}
{"id":180833347,"repository_id":4817619,"number":"3943","state":"finished","result":1,"started_at":"2016-12-02T21:38:02Z","finished_at":"2016-12-02T21:58:59Z","duration":1257,"commit":"de3458616face44624caf89abf80282dff3f5399","branch":"fix-961","message":"fix example test","event_type":"push"}
{"id":180803234,"repository_id":4817619,"number":"3942","state":"finished","result":null,"started_at":"2016-12-02T19:33:04Z","finished_at":"2016-12-02T20:22:25Z","duration":2961,"commit":"351acb24eb50a1690c667fe92dbef521d6a532ac","branch":"parallelize_rethink_2","message":"Deploy rethinkDB as a petset","event_type":"push"}
{"id":180800562,"repository_id":4817619,"number":"3941","state":"finished","result":1,"started_at":"2016-12-02T23:31:32Z","finished_at":"2016-12-03T00:06:09Z","duration":2077,"commit":"d6aee303f380cb7ff0488078314751fade4491c0","branch":"simple_service","message":"Make pps service construction DRYer\n\nAnd remove debug statements from test","event_type":"push"}
{"id":180635742,"repository_id":4817619,"number":"3940","state":"finished","result":0,"started_at":"2016-12-02T08:14:51Z","finished_at":"2016-12-02T08:35:27Z","duration":1236,"commit":"bc7c7f83de6a6ca6ea751ddc9f2163f4ea038f87","branch":"master","message":"Merge pull request #1097 from pachyderm/fix-845\n\nCorrest the output format of inspect-file","event_type":"push"}
{"id":180635656,"repository_id":4817619,"number":"3939","state":"finished","result":1,"started_at":"2016-12-02T08:14:51Z","finished_at":"2016-12-02T08:34:36Z","duration":1185,"commit":"18814d2effbd094259fb870b3eb62fc0cdca2066","branch":"master","message":"Merge pull request #1122 from pachyderm/fix-replay-help-message\n\nFix wrong help message for replay-commit","event_type":"push"}
{"id":180629053,"repository_id":4817619,"number":"3938","state":"finished","result":1,"started_at":"2016-12-02T07:23:53Z","finished_at":"2016-12-02T07:43:49Z","duration":1196,"commit":"cf4775740e40553855a90e41b11b5b478b5ac76a","branch":"master","message":"Merge pull request #1131 from orenyomtov/patch-1\n\nUpdate docs to change `pachctl deploy` to `pachctl deploy local`","event_type":"push"}
{"id":180594385,"repository_id":4817619,"number":"3935","state":"finished","result":1,"started_at":"2016-12-02T02:25:10Z","finished_at":"2016-12-02T02:58:21Z","duration":1991,"commit":"dde32f68453a86899a0bae5ceb49b9d82bed9a2d","branch":"pipe_input","message":"Propogate laziness to jorbs.","event_type":"push"}
{"id":180590423,"repository_id":4817619,"number":"3933","state":"finished","result":0,"started_at":"2016-12-02T01:57:38Z","finished_at":"2016-12-02T02:17:44Z","duration":1206,"commit":"b3c1b8924935abea11b2c5afdfb72e079f80b7b6","branch":"pipe_input","message":"Adds lazy printing to pachctl.","event_type":"push"}
{"id":180589421,"repository_id":4817619,"number":"3931","state":"finished","result":1,"started_at":"2016-12-02T01:50:46Z","finished_at":"2016-12-02T02:12:35Z","duration":1309,"commit":"7b62a35f99d2c12f930b5f7ea793665d3d842186","branch":"pipe_input","message":"Adds a test for lazy pipeline inputs.","event_type":"push"}
{"id":180583623,"repository_id":4817619,"number":"3930","state":"finished","result":0,"started_at":"2016-12-02T01:10:38Z","finished_at":"2016-12-02T01:37:28Z","duration":1610,"commit":"5b853935ddae6aa59309f3660ed48ee6bb49e5e1","branch":"jupyter_example","message":"Update run command for jupyter notebook job","event_type":"push"}
{"id":180555695,"repository_id":4817619,"number":"3929","state":"finished","result":1,"started_at":"2016-12-02T18:20:46Z","finished_at":"2016-12-02T18:57:57Z","duration":2231,"commit":"d3dcfbd8f24a7571fc516dd2c31bc0be3795e061","branch":"simple_service","message":"Omit pachctl flags for services","event_type":"push"}
{"id":178932658,"repository_id":4817619,"number":"3864","state":"finished","result":1,"started_at":"2016-11-25T21:02:24Z","finished_at":"2016-11-25T21:37:41Z","duration":2117,"commit":"c4cf3c939c1c6de95f2228fb07aa228985921dff","branch":"master","message":"Merge pull request #1095 from pachyderm/derekchiang-patch-7\n\nUpdate license badge","event_type":"push"}
